st_screen_stats/__init__.py
st_screen_stats/example.py
st_screen_stats/ScreenData/__init__.py
st_screen_stats/ScreenData/example.py
st_screen_stats/ScreenData/frontend/build/asset-manifest.json
st_screen_stats/ScreenData/frontend/build/bootstrap.min.css
st_screen_stats/ScreenData/frontend/build/bootstrap.min.css.map
st_screen_stats/ScreenData/frontend/build/index.html
st_screen_stats/ScreenData/frontend/build/static/js/main.065cdbcb.js
st_screen_stats/ScreenData/frontend/build/static/js/main.065cdbcb.js.LICENSE.txt
st_screen_stats/ScreenData/frontend/build/static/js/main.065cdbcb.js.map
st_screen_stats/ScreenStWidgets/__init__.py
st_screen_stats/WindowScreenQuery/__init__.py
st_screen_stats/WindowScreenQuery/example.py
st_screen_stats/WindowScreenQuery/frontend/build/asset-manifest.json
st_screen_stats/WindowScreenQuery/frontend/build/bootstrap.min.css
st_screen_stats/WindowScreenQuery/frontend/build/bootstrap.min.css.map
st_screen_stats/WindowScreenQuery/frontend/build/index.html
st_screen_stats/WindowScreenQuery/frontend/build/static/js/main.2c868ded.js
st_screen_stats/WindowScreenQuery/frontend/build/static/js/main.2c868ded.js.LICENSE.txt
st_screen_stats/WindowScreenQuery/frontend/build/static/js/main.2c868ded.js.map
streamlit_screen_stats_test_v1-0.0.2.dist-info/LICENSE
streamlit_screen_stats_test_v1-0.0.2.dist-info/METADATA
streamlit_screen_stats_test_v1-0.0.2.dist-info/WHEEL
streamlit_screen_stats_test_v1-0.0.2.dist-info/top_level.txt
streamlit_screen_stats_test_v1-0.0.2.dist-info/RECORD
